zyntra/__init__.py
zyntra/exts.py
zyntra-1.1.0.dist-info/licenses/LICENSE
zyntra-1.1.0.dist-info/METADATA
zyntra-1.1.0.dist-info/WHEEL
zyntra-1.1.0.dist-info/top_level.txt
zyntra-1.1.0.dist-info/RECORD
